tiktok_info/__init__.py
tiktok_info_zaem-1.0.0.dist-info/METADATA
tiktok_info_zaem-1.0.0.dist-info/WHEEL
tiktok_info_zaem-1.0.0.dist-info/top_level.txt
tiktok_info_zaem-1.0.0.dist-info/RECORD
