Metadata-Version: 2.4
Name: tiktok-info-zaem
Version: 1.0.0
Summary: TikTok user info library
Author: ZAEM
Requires-Dist: requests
Dynamic: author
Dynamic: requires-dist
Dynamic: summary
